tellit/__init__.py
tellit/cli.py
tellit/example_notification_sound.wav
tellit/exceptions.py
tellit/notify.py
tellit/os_notifiers/__init__.py
tellit/os_notifiers/_base.py
tellit/os_notifiers/binaries/Notificator.app/Contents/Info.plist
tellit/os_notifiers/binaries/Notificator.app/Contents/MacOS/applet
tellit/os_notifiers/binaries/Notificator.app/Contents/PkgInfo
tellit/os_notifiers/binaries/Notificator.app/Contents/Resources/applet.icns
tellit/os_notifiers/binaries/Notificator.app/Contents/Resources/applet.rsrc
tellit/os_notifiers/binaries/Notificator.app/Contents/Resources/Scripts/main.scpt
tellit/os_notifiers/binaries/Notificator.app/Contents/Resources/Scripts/notificator
tellit/os_notifiers/linux.py
tellit/os_notifiers/macos.py
tellit/os_notifiers/windows.py
tellit/py-logo.png
tellit-0.3.43.dist-info/entry_points.txt
tellit-0.3.43.dist-info/licenses/LICENSE
tellit-0.3.43.dist-info/METADATA
tellit-0.3.43.dist-info/WHEEL
tellit-0.3.43.dist-info/RECORD
