Metadata-Version: 2.4
Name: tellit
Version: 0.3.43
Summary: Cross-platform desktop notification library for Python
License: MIT
License-File: LICENSE
Author: Mustafa Mohamed
Author-email: mustafa@ms7m.me
Requires-Python: >=3.6,<4.0
Classifier: License :: OSI Approved :: MIT License
Classifier: Programming Language :: Python :: 3
Classifier: Programming Language :: Python :: 3.6
Classifier: Programming Language :: Python :: 3.7
Classifier: Programming Language :: Python :: 3.8
Classifier: Programming Language :: Python :: 3.9
Classifier: Programming Language :: Python :: 3.10
Classifier: Programming Language :: Python :: 3.11
Classifier: Programming Language :: Python :: 3.12
Classifier: Programming Language :: Python :: 3.13
Classifier: Programming Language :: Python :: 3.14
Requires-Dist: jeepney ; sys_platform == "linux"
Requires-Dist: loguru (>=0.5.3)
Project-URL: Documentation, https://github.com/mofanx/tellit
Project-URL: Repository, https://github.com/mofanx/tellit
